setup.py
tokitou/__init__.py
tokitou/tokitou.py
tokitou.egg-info/PKG-INFO
tokitou.egg-info/SOURCES.txt
tokitou.egg-info/dependency_links.txt
tokitou.egg-info/top_level.txt