Metadata-Version: 1.0
Name: tokitou
Version: 0.1
Summary: Simple css preprocessing via python
Home-page: https://github.com/zhangxiansheng/tokitou
Author: Zhang Yiwei
Author-email: Karl1991223@126.com
License: public domain
Keywords: css,preprocess,preprocessing,tokitou,python
Platform: any
